{"enabled":true,"neededInstalledMods":[],"neededUninstalledMods":[],"spawns":[{"id":"alpha-swoobat-1","pokemon":"swoobat alpha","presets":["natural","treetop"],"type":"pokemon","context":"grounded","bucket":"common","level":"27-43","weight":0.3333333333333333,"condition":{"minSkyLight":8,"maxSkyLight":15,"biomes":["#cobblemon:is_jungle","#cobblemon:is_savanna"],"timeRange":"night","isRaining":false}},{"id":"alpha-swoobat-3","pokemon":"swoobat alpha","presets":["natural"],"type":"pokemon","context":"grounded","bucket":"common","level":"27-43","weight":0.3333333333333333,"weightMultiplier":{"multiplier":0.25,"condition":{"timeRange":"night"}},"condition":{"minSkyLight":0,"maxSkyLight":7,"biomes":["#cobblemon:is_jungle","#cobblemon:is_savanna"]}}]}